{
  "file_name": "doc_03225.png",
  "annotations": [
    {
      "bbox": [
        111.84,
        362.21,
        385.49,
        23.07
      ],
      "category_id": 1,
      "category_name": ""
    },
    {
      "bbox": [
        111.84,
        390.72,
        385.54,
        58.33
      ],
      "category_id": 1,
      "category_name": ""
    },
    {
      "bbox": [
        111.84,
        454.44,
        385.6,
        46.63
      ],
      "category_id": 1,
      "category_name": ""
    },
    {
      "bbox": [
        111.84,
        506.45,
        385.61,
        34.83
      ],
      "category_id": 1,
      "category_name": ""
    },
    {
      "bbox": [
        313.08,
        579.64,
        241.03,
        116.91
      ],
      "category_id": 1,
      "category_name": ""
    },
    {
      "bbox": [
        55.14,
        591.39,
        240.99,
        140.37
      ],
      "category_id": 1,
      "category_name": ""
    },
    {
      "bbox": [
        55.14,
        294.55,
        492.36,
        18.74
      ],
      "category_id": 1,
      "category_name": ""
    },
    {
      "bbox": [
        55.14,
        174.12,
        338.7,
        9.14
      ],
      "category_id": 1,
      "category_name": ""
    },
    {
      "bbox": [
        55.14,
        137.37,
        267.64,
        17.18
      ],
      "category_id": 1,
      "category_name": ""
    },
    {
      "bbox": [
        55.14,
        100.49,
        499.4,
        36.86
      ],
      "category_id": 2,
      "category_name": ""
    },
    {
      "bbox": [
        111.84,
        346.93,
        43.92,
        12.66
      ],
      "category_id": 2,
      "category_name": ""
    },
    {
      "bbox": [
        55.14,
        578.95,
        60.3,
        12.66
      ],
      "category_id": 2,
      "category_name": ""
    }
  ],
  "corruption": {
    "type": "none",
    "severity": 0
  }
}