{
  "file_name": "doc_02686.png",
  "annotations": [
    {
      "bbox": [
        45.01,
        381.82,
        243.0,
        121.84
      ],
      "category_id": 1,
      "category_name": ""
    },
    {
      "bbox": [
        45.01,
        504.56,
        242.96,
        32.6
      ],
      "category_id": 1,
      "category_name": ""
    },
    {
      "bbox": [
        44.1,
        538.07,
        243.91,
        121.84
      ],
      "category_id": 1,
      "category_name": ""
    },
    {
      "bbox": [
        306.03,
        46.82,
        242.97,
        99.22
      ],
      "category_id": 1,
      "category_name": ""
    },
    {
      "bbox": [
        45.01,
        660.64,
        242.99,
        66.22
      ],
      "category_id": 1,
      "category_name": ""
    },
    {
      "bbox": [
        305.12,
        146.64,
        243.88,
        54.44
      ],
      "category_id": 1,
      "category_name": ""
    },
    {
      "bbox": [
        306.02,
        201.82,
        242.97,
        98.31
      ],
      "category_id": 1,
      "category_name": ""
    },
    {
      "bbox": [
        306.02,
        300.91,
        242.96,
        21.26
      ],
      "category_id": 1,
      "category_name": ""
    },
    {
      "bbox": [
        306.02,
        322.91,
        242.96,
        43.27
      ],
      "category_id": 1,
      "category_name": ""
    },
    {
      "bbox": [
        306.03,
        366.97,
        242.98,
        76.31
      ],
      "category_id": 1,
      "category_name": ""
    },
    {
      "bbox": [
        306.03,
        444.01,
        243.88,
        87.35
      ],
      "category_id": 1,
      "category_name": ""
    },
    {
      "bbox": [
        306.03,
        573.5,
        242.99,
        76.31
      ],
      "category_id": 1,
      "category_name": ""
    },
    {
      "bbox": [
        306.03,
        650.55,
        242.99,
        76.31
      ],
      "category_id": 1,
      "category_name": ""
    },
    {
      "bbox": [
        54.03,
        58.44,
        233.94,
        19.87
      ],
      "category_id": 1,
      "category_name": ""
    },
    {
      "bbox": [
        54.03,
        94.82,
        234.05,
        271.25
      ],
      "category_id": 4,
      "category_name": ""
    },
    {
      "bbox": [
        306.03,
        545.98,
        61.3,
        11.33
      ],
      "category_id": 2,
      "category_name": ""
    },
    {
      "bbox": [
        306.03,
        562.23,
        63.35,
        10.35
      ],
      "category_id": 2,
      "category_name": ""
    }
  ],
  "corruption": {
    "type": "none",
    "severity": 0
  }
}