{
  "file_name": "doc_04426.png",
  "annotations": [
    {
      "bbox": [
        55.2,
        81.37,
        238.82,
        187.2
      ],
      "category_id": 1,
      "category_name": ""
    },
    {
      "bbox": [
        55.2,
        268.33,
        238.81,
        88.2
      ],
      "category_id": 1,
      "category_name": ""
    },
    {
      "bbox": [
        55.2,
        455.41,
        238.86,
        198.12
      ],
      "category_id": 1,
      "category_name": ""
    },
    {
      "bbox": [
        318.0,
        81.37,
        238.83,
        231.12
      ],
      "category_id": 1,
      "category_name": ""
    },
    {
      "bbox": [
        55.2,
        653.41,
        238.82,
        77.16
      ],
      "category_id": 1,
      "category_name": ""
    },
    {
      "bbox": [
        318.0,
        312.37,
        238.83,
        209.16
      ],
      "category_id": 1,
      "category_name": ""
    },
    {
      "bbox": [
        318.0,
        598.33,
        238.83,
        77.16
      ],
      "category_id": 1,
      "category_name": ""
    },
    {
      "bbox": [
        318.0,
        708.35,
        238.81,
        22.22
      ],
      "category_id": 1,
      "category_name": ""
    },
    {
      "bbox": [
        55.2,
        367.33,
        238.86,
        77.16
      ],
      "category_id": 3,
      "category_name": ""
    },
    {
      "bbox": [
        318.0,
        532.3,
        238.8,
        55.23
      ],
      "category_id": 3,
      "category_name": ""
    },
    {
      "bbox": [
        318.0,
        685.08,
        90.62,
        12.5
      ],
      "category_id": 2,
      "category_name": ""
    }
  ],
  "corruption": {
    "type": "blur",
    "severity": 2
  }
}