{
  "file_name": "doc_03660.png",
  "annotations": [
    {
      "bbox": [
        55.2,
        81.37,
        238.82,
        121.2
      ],
      "category_id": 1,
      "category_name": ""
    },
    {
      "bbox": [
        55.2,
        235.33,
        238.82,
        55.2
      ],
      "category_id": 1,
      "category_name": ""
    },
    {
      "bbox": [
        55.2,
        290.41,
        238.82,
        77.16
      ],
      "category_id": 1,
      "category_name": ""
    },
    {
      "bbox": [
        318.0,
        81.37,
        238.82,
        55.2
      ],
      "category_id": 1,
      "category_name": ""
    },
    {
      "bbox": [
        55.2,
        653.41,
        238.8,
        77.16
      ],
      "category_id": 1,
      "category_name": ""
    },
    {
      "bbox": [
        318.0,
        136.13,
        238.83,
        165.44
      ],
      "category_id": 1,
      "category_name": ""
    },
    {
      "bbox": [
        318.0,
        334.33,
        238.86,
        154.2
      ],
      "category_id": 1,
      "category_name": ""
    },
    {
      "bbox": [
        318.0,
        488.41,
        238.81,
        66.12
      ],
      "category_id": 1,
      "category_name": ""
    },
    {
      "bbox": [
        318.0,
        554.41,
        238.82,
        77.16
      ],
      "category_id": 1,
      "category_name": ""
    },
    {
      "bbox": [
        318.0,
        664.33,
        238.82,
        66.24
      ],
      "category_id": 1,
      "category_name": ""
    },
    {
      "bbox": [
        55.2,
        399.81,
        238.82,
        176.68
      ],
      "category_id": 3,
      "category_name": ""
    },
    {
      "bbox": [
        55.2,
        609.37,
        168.85,
        11.16
      ],
      "category_id": 3,
      "category_name": ""
    },
    {
      "bbox": [
        55.2,
        212.53,
        39.72,
        12.11
      ],
      "category_id": 2,
      "category_name": ""
    },
    {
      "bbox": [
        55.2,
        377.53,
        101.4,
        12.11
      ],
      "category_id": 2,
      "category_name": ""
    },
    {
      "bbox": [
        55.2,
        586.57,
        151.19,
        12.11
      ],
      "category_id": 2,
      "category_name": ""
    },
    {
      "bbox": [
        55.2,
        630.0,
        135.75,
        12.5
      ],
      "category_id": 2,
      "category_name": ""
    },
    {
      "bbox": [
        318.0,
        311.32,
        163.33,
        12.32
      ],
      "category_id": 2,
      "category_name": ""
    },
    {
      "bbox": [
        318.0,
        641.53,
        108.12,
        12.11
      ],
      "category_id": 2,
      "category_name": ""
    }
  ],
  "corruption": {
    "type": "none",
    "severity": 0
  }
}