{
  "file_name": "doc_00995.png",
  "annotations": [
    {
      "bbox": [
        55.14,
        425.43,
        240.98,
        58.11
      ],
      "category_id": 1,
      "category_name": ""
    },
    {
      "bbox": [
        55.14,
        507.68,
        240.98,
        140.39
      ],
      "category_id": 1,
      "category_name": ""
    },
    {
      "bbox": [
        313.08,
        425.44,
        240.98,
        128.61
      ],
      "category_id": 1,
      "category_name": ""
    },
    {
      "bbox": [
        55.14,
        660.46,
        240.98,
        69.87
      ],
      "category_id": 1,
      "category_name": ""
    },
    {
      "bbox": [
        313.08,
        578.19,
        241.04,
        152.13
      ],
      "category_id": 1,
      "category_name": ""
    },
    {
      "bbox": [
        55.14,
        84.77,
        342.09,
        9.41
      ],
      "category_id": 1,
      "category_name": ""
    },
    {
      "bbox": [
        59.1,
        357.78,
        490.94,
        55.83
      ],
      "category_id": 1,
      "category_name": ""
    },
    {
      "bbox": [
        55.14,
        100.8,
        498.9,
        251.34
      ],
      "category_id": 4,
      "category_name": ""
    },
    {
      "bbox": [
        55.14,
        495.74,
        104.46,
        11.04
      ],
      "category_id": 2,
      "category_name": ""
    },
    {
      "bbox": [
        313.08,
        566.24,
        118.53,
        11.04
      ],
      "category_id": 2,
      "category_name": ""
    }
  ],
  "corruption": {
    "type": "none",
    "severity": 0
  }
}