{
  "file_name": "doc_04212.png",
  "annotations": [
    {
      "bbox": [
        55.14,
        366.69,
        240.98,
        93.39
      ],
      "category_id": 1,
      "category_name": ""
    },
    {
      "bbox": [
        55.14,
        484.17,
        240.99,
        152.13
      ],
      "category_id": 1,
      "category_name": ""
    },
    {
      "bbox": [
        313.08,
        84.7,
        240.98,
        116.85
      ],
      "category_id": 1,
      "category_name": ""
    },
    {
      "bbox": [
        55.14,
        648.7,
        240.99,
        81.63
      ],
      "category_id": 1,
      "category_name": ""
    },
    {
      "bbox": [
        313.08,
        213.94,
        241.05,
        375.4
      ],
      "category_id": 1,
      "category_name": ""
    },
    {
      "bbox": [
        313.08,
        613.41,
        240.95,
        22.89
      ],
      "category_id": 1,
      "category_name": ""
    },
    {
      "bbox": [
        313.08,
        660.45,
        240.98,
        69.87
      ],
      "category_id": 1,
      "category_name": ""
    },
    {
      "bbox": [
        55.14,
        287.17,
        235.8,
        32.76
      ],
      "category_id": 1,
      "category_name": ""
    },
    {
      "bbox": [
        57.36,
        94.92,
        236.46,
        167.1
      ],
      "category_id": 5,
      "category_name": ""
    },
    {
      "bbox": [
        55.14,
        354.74,
        79.34,
        11.04
      ],
      "category_id": 2,
      "category_name": ""
    },
    {
      "bbox": [
        55.14,
        471.73,
        52.56,
        12.66
      ],
      "category_id": 2,
      "category_name": ""
    },
    {
      "bbox": [
        313.08,
        601.03,
        103.24,
        12.66
      ],
      "category_id": 2,
      "category_name": ""
    },
    {
      "bbox": [
        313.08,
        648.01,
        113.69,
        12.66
      ],
      "category_id": 2,
      "category_name": ""
    }
  ],
  "corruption": {
    "type": "none",
    "severity": 0
  }
}