{
  "file_name": "doc_00072.png",
  "annotations": [
    {
      "bbox": [
        55.14,
        530.91,
        240.97,
        69.93
      ],
      "category_id": 1,
      "category_name": ""
    },
    {
      "bbox": [
        55.14,
        624.93,
        240.99,
        105.15
      ],
      "category_id": 1,
      "category_name": ""
    },
    {
      "bbox": [
        313.08,
        530.92,
        240.98,
        69.93
      ],
      "category_id": 1,
      "category_name": ""
    },
    {
      "bbox": [
        313.08,
        613.18,
        240.98,
        116.91
      ],
      "category_id": 1,
      "category_name": ""
    },
    {
      "bbox": [
        55.14,
        368.72,
        499.15,
        89.2
      ],
      "category_id": 1,
      "category_name": ""
    },
    {
      "bbox": [
        85.14,
        467.59,
        123.65,
        11.28
      ],
      "category_id": 1,
      "category_name": ""
    },
    {
      "bbox": [
        252.47,
        466.6,
        239.31,
        14.0
      ],
      "category_id": 1,
      "category_name": ""
    },
    {
      "bbox": [
        55.14,
        87.0,
        498.9,
        275.28
      ],
      "category_id": 5,
      "category_name": ""
    },
    {
      "bbox": [
        55.14,
        612.49,
        35.98,
        12.66
      ],
      "category_id": 2,
      "category_name": ""
    }
  ],
  "corruption": {
    "type": "none",
    "severity": 0
  }
}