{
  "file_name": "doc_02169.png",
  "annotations": [
    {
      "bbox": [
        55.14,
        495.93,
        240.98,
        116.91
      ],
      "category_id": 1,
      "category_name": ""
    },
    {
      "bbox": [
        313.08,
        495.94,
        240.98,
        93.39
      ],
      "category_id": 1,
      "category_name": ""
    },
    {
      "bbox": [
        55.14,
        625.18,
        240.98,
        105.15
      ],
      "category_id": 1,
      "category_name": ""
    },
    {
      "bbox": [
        313.08,
        601.72,
        240.98,
        128.61
      ],
      "category_id": 1,
      "category_name": ""
    },
    {
      "bbox": [
        55.14,
        84.77,
        213.21,
        9.41
      ],
      "category_id": 1,
      "category_name": ""
    },
    {
      "bbox": [
        59.1,
        471.15,
        483.77,
        18.78
      ],
      "category_id": 1,
      "category_name": ""
    },
    {
      "bbox": [
        55.14,
        100.8,
        498.9,
        364.68
      ],
      "category_id": 4,
      "category_name": ""
    }
  ],
  "corruption": {
    "type": "none",
    "severity": 0
  }
}