{
  "file_name": "doc_04906.png",
  "annotations": [
    {
      "bbox": [
        313.08,
        343.18,
        240.96,
        22.89
      ],
      "category_id": 1,
      "category_name": ""
    },
    {
      "bbox": [
        55.14,
        354.93,
        240.98,
        105.15
      ],
      "category_id": 1,
      "category_name": ""
    },
    {
      "bbox": [
        313.08,
        390.15,
        240.98,
        83.4
      ],
      "category_id": 1,
      "category_name": ""
    },
    {
      "bbox": [
        55.14,
        84.39,
        381.51,
        11.22
      ],
      "category_id": 1,
      "category_name": ""
    },
    {
      "bbox": [
        55.14,
        489.93,
        293.89,
        11.33
      ],
      "category_id": 1,
      "category_name": ""
    },
    {
      "bbox": [
        59.1,
        302.31,
        491.12,
        28.08
      ],
      "category_id": 1,
      "category_name": ""
    },
    {
      "bbox": [
        59.1,
        707.91,
        490.32,
        28.08
      ],
      "category_id": 1,
      "category_name": ""
    },
    {
      "bbox": [
        55.14,
        102.0,
        498.9,
        194.64
      ],
      "category_id": 4,
      "category_name": ""
    },
    {
      "bbox": [
        55.14,
        507.6,
        498.9,
        194.64
      ],
      "category_id": 4,
      "category_name": ""
    },
    {
      "bbox": [
        55.14,
        342.98,
        234.89,
        11.04
      ],
      "category_id": 2,
      "category_name": ""
    },
    {
      "bbox": [
        313.08,
        378.26,
        206.74,
        11.04
      ],
      "category_id": 2,
      "category_name": ""
    }
  ],
  "corruption": {
    "type": "rotate",
    "severity": 3
  }
}