{
  "file_name": "doc_03833.png",
  "annotations": [
    {
      "bbox": [
        52.09,
        411.51,
        240.1,
        22.04
      ],
      "category_id": 1,
      "category_name": ""
    },
    {
      "bbox": [
        52.09,
        434.43,
        240.11,
        205.35
      ],
      "category_id": 1,
      "category_name": ""
    },
    {
      "bbox": [
        310.12,
        388.6,
        240.17,
        285.55
      ],
      "category_id": 1,
      "category_name": ""
    },
    {
      "bbox": [
        52.09,
        640.65,
        240.11,
        102.24
      ],
      "category_id": 1,
      "category_name": ""
    },
    {
      "bbox": [
        310.12,
        675.02,
        240.13,
        67.87
      ],
      "category_id": 1,
      "category_name": ""
    },
    {
      "bbox": [
        52.09,
        295.88,
        240.11,
        82.92
      ],
      "category_id": 1,
      "category_name": ""
    },
    {
      "bbox": [
        310.12,
        295.89,
        240.14,
        61.98
      ],
      "category_id": 1,
      "category_name": ""
    },
    {
      "bbox": [
        58.79,
        72.04,
        226.44,
        209.41
      ],
      "category_id": 5,
      "category_name": ""
    },
    {
      "bbox": [
        315.83,
        72.04,
        226.44,
        209.41
      ],
      "category_id": 5,
      "category_name": ""
    }
  ],
  "corruption": {
    "type": "none",
    "severity": 0
  }
}