{
  "file_name": "doc_02300.png",
  "annotations": [
    {
      "bbox": [
        55.14,
        225.69,
        240.98,
        46.35
      ],
      "category_id": 1,
      "category_name": ""
    },
    {
      "bbox": [
        55.14,
        284.44,
        240.99,
        234.39
      ],
      "category_id": 1,
      "category_name": ""
    },
    {
      "bbox": [
        313.08,
        84.7,
        241.04,
        210.87
      ],
      "category_id": 1,
      "category_name": ""
    },
    {
      "bbox": [
        55.14,
        531.16,
        240.99,
        199.17
      ],
      "category_id": 1,
      "category_name": ""
    },
    {
      "bbox": [
        313.08,
        307.96,
        240.98,
        163.83
      ],
      "category_id": 1,
      "category_name": ""
    },
    {
      "bbox": [
        313.08,
        495.93,
        241.02,
        187.41
      ],
      "category_id": 1,
      "category_name": ""
    },
    {
      "bbox": [
        313.08,
        707.43,
        240.95,
        22.89
      ],
      "category_id": 1,
      "category_name": ""
    },
    {
      "bbox": [
        55.14,
        84.77,
        229.37,
        18.89
      ],
      "category_id": 1,
      "category_name": ""
    },
    {
      "bbox": [
        59.1,
        187.54,
        227.56,
        9.59
      ],
      "category_id": 1,
      "category_name": ""
    },
    {
      "bbox": [
        55.14,
        110.28,
        241.98,
        71.64
      ],
      "category_id": 4,
      "category_name": ""
    },
    {
      "bbox": [
        313.08,
        483.49,
        55.56,
        12.66
      ],
      "category_id": 2,
      "category_name": ""
    },
    {
      "bbox": [
        313.08,
        694.99,
        103.22,
        12.66
      ],
      "category_id": 2,
      "category_name": ""
    }
  ],
  "corruption": {
    "type": "none",
    "severity": 0
  }
}