{
  "file_name": "doc_04807.png",
  "annotations": [
    {
      "bbox": [
        52.07,
        357.84,
        240.13,
        147.0
      ],
      "category_id": 1,
      "category_name": ""
    },
    {
      "bbox": [
        52.07,
        560.93,
        240.11,
        101.53
      ],
      "category_id": 1,
      "category_name": ""
    },
    {
      "bbox": [
        310.1,
        72.42,
        240.12,
        124.64
      ],
      "category_id": 1,
      "category_name": ""
    },
    {
      "bbox": [
        52.07,
        698.22,
        240.13,
        44.68
      ],
      "category_id": 1,
      "category_name": ""
    },
    {
      "bbox": [
        310.1,
        231.98,
        240.11,
        169.73
      ],
      "category_id": 1,
      "category_name": ""
    },
    {
      "bbox": [
        310.1,
        436.65,
        240.13,
        90.15
      ],
      "category_id": 1,
      "category_name": ""
    },
    {
      "bbox": [
        310.11,
        573.11,
        240.13,
        90.16
      ],
      "category_id": 1,
      "category_name": ""
    },
    {
      "bbox": [
        310.11,
        698.21,
        240.12,
        44.68
      ],
      "category_id": 1,
      "category_name": ""
    },
    {
      "bbox": [
        52.07,
        72.78,
        240.16,
        249.3
      ],
      "category_id": 3,
      "category_name": ""
    },
    {
      "bbox": [
        52.07,
        336.92,
        78.11,
        10.77
      ],
      "category_id": 2,
      "category_name": ""
    },
    {
      "bbox": [
        52.07,
        519.47,
        56.28,
        10.97
      ],
      "category_id": 2,
      "category_name": ""
    },
    {
      "bbox": [
        52.07,
        540.0,
        51.74,
        10.77
      ],
      "category_id": 2,
      "category_name": ""
    },
    {
      "bbox": [
        52.07,
        677.29,
        210.49,
        10.77
      ],
      "category_id": 2,
      "category_name": ""
    },
    {
      "bbox": [
        310.1,
        211.47,
        221.26,
        10.77
      ],
      "category_id": 2,
      "category_name": ""
    },
    {
      "bbox": [
        310.1,
        416.13,
        185.06,
        10.77
      ],
      "category_id": 2,
      "category_name": ""
    },
    {
      "bbox": [
        310.11,
        541.23,
        176.98,
        22.14
      ],
      "category_id": 2,
      "category_name": ""
    },
    {
      "bbox": [
        310.11,
        677.7,
        193.57,
        10.77
      ],
      "category_id": 2,
      "category_name": ""
    }
  ],
  "corruption": {
    "type": "none",
    "severity": 0
  }
}