{
  "file_name": "doc_01109.png",
  "annotations": [
    {
      "bbox": [
        55.14,
        484.17,
        240.98,
        58.11
      ],
      "category_id": 1,
      "category_name": ""
    },
    {
      "bbox": [
        55.14,
        554.68,
        240.98,
        128.67
      ],
      "category_id": 1,
      "category_name": ""
    },
    {
      "bbox": [
        313.08,
        484.18,
        240.99,
        58.11
      ],
      "category_id": 1,
      "category_name": ""
    },
    {
      "bbox": [
        55.14,
        695.68,
        240.97,
        34.65
      ],
      "category_id": 1,
      "category_name": ""
    },
    {
      "bbox": [
        313.08,
        566.43,
        240.99,
        163.89
      ],
      "category_id": 1,
      "category_name": ""
    },
    {
      "bbox": [
        55.14,
        361.15,
        498.97,
        65.04
      ],
      "category_id": 1,
      "category_name": ""
    },
    {
      "bbox": [
        55.14,
        87.0,
        498.9,
        267.72
      ],
      "category_id": 5,
      "category_name": ""
    },
    {
      "bbox": [
        313.08,
        554.48,
        150.34,
        11.04
      ],
      "category_id": 2,
      "category_name": ""
    }
  ],
  "corruption": {
    "type": "none",
    "severity": 0
  }
}