{
  "file_name": "doc_01530.png",
  "annotations": [
    {
      "bbox": [
        55.14,
        84.69,
        240.98,
        105.09
      ],
      "category_id": 1,
      "category_name": ""
    },
    {
      "bbox": [
        55.14,
        202.18,
        240.98,
        152.13
      ],
      "category_id": 1,
      "category_name": ""
    },
    {
      "bbox": [
        313.08,
        84.7,
        240.99,
        69.87
      ],
      "category_id": 1,
      "category_name": ""
    },
    {
      "bbox": [
        55.14,
        366.7,
        241.0,
        152.13
      ],
      "category_id": 1,
      "category_name": ""
    },
    {
      "bbox": [
        313.08,
        190.41,
        241.01,
        257.91
      ],
      "category_id": 1,
      "category_name": ""
    },
    {
      "bbox": [
        313.08,
        472.41,
        241.03,
        46.41
      ],
      "category_id": 1,
      "category_name": ""
    },
    {
      "bbox": [
        55.14,
        527.81,
        468.22,
        9.41
      ],
      "category_id": 1,
      "category_name": ""
    },
    {
      "bbox": [
        59.1,
        690.93,
        481.76,
        37.26
      ],
      "category_id": 1,
      "category_name": ""
    },
    {
      "bbox": [
        55.14,
        543.84,
        498.9,
        141.42
      ],
      "category_id": 4,
      "category_name": ""
    },
    {
      "bbox": [
        313.08,
        166.27,
        43.28,
        12.66
      ],
      "category_id": 2,
      "category_name": ""
    },
    {
      "bbox": [
        313.08,
        178.46,
        50.12,
        11.04
      ],
      "category_id": 2,
      "category_name": ""
    },
    {
      "bbox": [
        313.08,
        460.52,
        103.7,
        11.04
      ],
      "category_id": 2,
      "category_name": ""
    }
  ],
  "corruption": {
    "type": "none",
    "severity": 0
  }
}