{
  "file_name": "doc_04015.png",
  "annotations": [
    {
      "bbox": [
        55.2,
        135.85,
        238.81,
        22.2
      ],
      "category_id": 1,
      "category_name": ""
    },
    {
      "bbox": [
        55.2,
        286.94,
        238.81,
        44.63
      ],
      "category_id": 1,
      "category_name": ""
    },
    {
      "bbox": [
        55.2,
        384.05,
        238.79,
        22.52
      ],
      "category_id": 1,
      "category_name": ""
    },
    {
      "bbox": [
        318.0,
        81.37,
        238.82,
        165.12
      ],
      "category_id": 1,
      "category_name": ""
    },
    {
      "bbox": [
        55.2,
        459.82,
        238.82,
        121.71
      ],
      "category_id": 1,
      "category_name": ""
    },
    {
      "bbox": [
        318.0,
        245.9,
        238.79,
        22.67
      ],
      "category_id": 1,
      "category_name": ""
    },
    {
      "bbox": [
        318.0,
        273.73,
        238.82,
        198.24
      ],
      "category_id": 1,
      "category_name": ""
    },
    {
      "bbox": [
        318.0,
        471.34,
        238.8,
        110.67
      ],
      "category_id": 1,
      "category_name": ""
    },
    {
      "bbox": [
        55.2,
        597.06,
        211.78,
        10.53
      ],
      "category_id": 1,
      "category_name": ""
    },
    {
      "bbox": [
        55.2,
        720.07,
        376.89,
        10.53
      ],
      "category_id": 1,
      "category_name": ""
    },
    {
      "bbox": [
        55.2,
        613.8,
        501.6,
        102.0
      ],
      "category_id": 4,
      "category_name": ""
    },
    {
      "bbox": [
        55.2,
        81.37,
        238.81,
        44.16
      ],
      "category_id": 3,
      "category_name": ""
    },
    {
      "bbox": [
        55.2,
        168.37,
        238.82,
        88.2
      ],
      "category_id": 3,
      "category_name": ""
    },
    {
      "bbox": [
        55.2,
        265.57,
        135.37,
        12.11
      ],
      "category_id": 2,
      "category_name": ""
    },
    {
      "bbox": [
        55.2,
        341.04,
        67.32,
        12.5
      ],
      "category_id": 2,
      "category_name": ""
    },
    {
      "bbox": [
        55.2,
        362.53,
        133.94,
        12.11
      ],
      "category_id": 2,
      "category_name": ""
    },
    {
      "bbox": [
        55.2,
        416.53,
        63.24,
        12.11
      ],
      "category_id": 2,
      "category_name": ""
    },
    {
      "bbox": [
        55.2,
        438.14,
        212.31,
        22.43
      ],
      "category_id": 2,
      "category_name": ""
    }
  ],
  "corruption": {
    "type": "none",
    "severity": 0
  }
}