{
  "file_name": "doc_02352.png",
  "annotations": [
    {
      "bbox": [
        313.08,
        84.7,
        240.99,
        105.09
      ],
      "category_id": 1,
      "category_name": ""
    },
    {
      "bbox": [
        55.14,
        413.67,
        240.99,
        316.65
      ],
      "category_id": 1,
      "category_name": ""
    },
    {
      "bbox": [
        313.08,
        202.18,
        241.02,
        116.91
      ],
      "category_id": 1,
      "category_name": ""
    },
    {
      "bbox": [
        313.08,
        331.42,
        241.02,
        187.41
      ],
      "category_id": 1,
      "category_name": ""
    },
    {
      "bbox": [
        313.08,
        531.16,
        241.04,
        199.16
      ],
      "category_id": 1,
      "category_name": ""
    },
    {
      "bbox": [
        55.14,
        84.77,
        236.08,
        18.89
      ],
      "category_id": 1,
      "category_name": ""
    },
    {
      "bbox": [
        55.02,
        110.28,
        242.1,
        286.92
      ],
      "category_id": 4,
      "category_name": ""
    }
  ],
  "corruption": {
    "type": "noise",
    "severity": 3
  }
}