{
  "file_name": "doc_00341.png",
  "annotations": [
    {
      "bbox": [
        55.14,
        474.44,
        240.97,
        34.66
      ],
      "category_id": 1,
      "category_name": ""
    },
    {
      "bbox": [
        55.14,
        521.5,
        240.98,
        128.61
      ],
      "category_id": 1,
      "category_name": ""
    },
    {
      "bbox": [
        55.14,
        686.01,
        240.99,
        46.35
      ],
      "category_id": 1,
      "category_name": ""
    },
    {
      "bbox": [
        55.14,
        84.77,
        161.6,
        9.41
      ],
      "category_id": 1,
      "category_name": ""
    },
    {
      "bbox": [
        55.14,
        274.55,
        466.17,
        9.41
      ],
      "category_id": 1,
      "category_name": ""
    },
    {
      "bbox": [
        313.08,
        474.59,
        228.95,
        18.89
      ],
      "category_id": 1,
      "category_name": ""
    },
    {
      "bbox": [
        59.1,
        209.31,
        491.05,
        37.26
      ],
      "category_id": 1,
      "category_name": ""
    },
    {
      "bbox": [
        59.1,
        409.35,
        491.28,
        37.26
      ],
      "category_id": 1,
      "category_name": ""
    },
    {
      "bbox": [
        317.1,
        615.69,
        234.15,
        83.52
      ],
      "category_id": 1,
      "category_name": ""
    },
    {
      "bbox": [
        55.14,
        100.8,
        498.78,
        97.5
      ],
      "category_id": 4,
      "category_name": ""
    },
    {
      "bbox": [
        55.14,
        290.58,
        499.02,
        107.76
      ],
      "category_id": 4,
      "category_name": ""
    },
    {
      "bbox": [
        313.08,
        500.1,
        242.04,
        104.58
      ],
      "category_id": 4,
      "category_name": ""
    },
    {
      "bbox": [
        55.14,
        662.3,
        219.64,
        22.8
      ],
      "category_id": 2,
      "category_name": ""
    }
  ],
  "corruption": {
    "type": "none",
    "severity": 0
  }
}