{
  "file_name": "doc_00768.png",
  "annotations": [
    {
      "bbox": [
        55.14,
        695.67,
        240.99,
        34.65
      ],
      "category_id": 1,
      "category_name": ""
    },
    {
      "bbox": [
        313.08,
        695.67,
        240.96,
        34.65
      ],
      "category_id": 1,
      "category_name": ""
    },
    {
      "bbox": [
        55.14,
        566.29,
        499.3,
        75.78
      ],
      "category_id": 1,
      "category_name": ""
    },
    {
      "bbox": [
        55.12,
        87.0,
        498.92,
        472.86
      ],
      "category_id": 5,
      "category_name": ""
    }
  ],
  "corruption": {
    "type": "none",
    "severity": 0
  }
}