{
  "file_name": "doc_03524.png",
  "annotations": [
    {
      "bbox": [
        55.14,
        307.95,
        240.99,
        187.35
      ],
      "category_id": 1,
      "category_name": ""
    },
    {
      "bbox": [
        55.14,
        519.45,
        240.99,
        93.39
      ],
      "category_id": 1,
      "category_name": ""
    },
    {
      "bbox": [
        313.08,
        307.96,
        240.97,
        69.87
      ],
      "category_id": 1,
      "category_name": ""
    },
    {
      "bbox": [
        55.14,
        648.69,
        240.99,
        81.63
      ],
      "category_id": 1,
      "category_name": ""
    },
    {
      "bbox": [
        313.08,
        425.43,
        240.99,
        81.63
      ],
      "category_id": 1,
      "category_name": ""
    },
    {
      "bbox": [
        313.08,
        542.91,
        241.02,
        187.41
      ],
      "category_id": 1,
      "category_name": ""
    },
    {
      "bbox": [
        55.14,
        100.8,
        498.9,
        194.64
      ],
      "category_id": 4,
      "category_name": ""
    },
    {
      "bbox": [
        55.14,
        507.5,
        208.96,
        11.04
      ],
      "category_id": 2,
      "category_name": ""
    },
    {
      "bbox": [
        55.14,
        624.98,
        215.11,
        22.8
      ],
      "category_id": 2,
      "category_name": ""
    },
    {
      "bbox": [
        313.08,
        401.72,
        241.32,
        22.8
      ],
      "category_id": 2,
      "category_name": ""
    },
    {
      "bbox": [
        313.08,
        519.26,
        205.49,
        22.8
      ],
      "category_id": 2,
      "category_name": ""
    },
    {
      "bbox": [
        55.14,
        84.77,
        32.25,
        9.41
      ],
      "category_id": 2,
      "category_name": ""
    }
  ],
  "corruption": {
    "type": "rotate",
    "severity": 3
  }
}