{
  "file_name": "doc_02690.png",
  "annotations": [
    {
      "bbox": [
        56.82,
        312.95,
        240.48,
        53.08
      ],
      "category_id": 1,
      "category_name": ""
    },
    {
      "bbox": [
        315.3,
        313.28,
        240.53,
        31.75
      ],
      "category_id": 1,
      "category_name": ""
    },
    {
      "bbox": [
        56.82,
        376.02,
        240.54,
        147.51
      ],
      "category_id": 1,
      "category_name": ""
    },
    {
      "bbox": [
        315.3,
        354.36,
        240.61,
        116.67
      ],
      "category_id": 1,
      "category_name": ""
    },
    {
      "bbox": [
        315.3,
        480.98,
        240.53,
        42.55
      ],
      "category_id": 1,
      "category_name": ""
    },
    {
      "bbox": [
        315.3,
        562.29,
        240.54,
        106.71
      ],
      "category_id": 1,
      "category_name": ""
    },
    {
      "bbox": [
        56.82,
        574.05,
        240.52,
        104.99
      ],
      "category_id": 1,
      "category_name": ""
    },
    {
      "bbox": [
        56.82,
        693.11,
        499.4,
        47.51
      ],
      "category_id": 1,
      "category_name": ""
    },
    {
      "bbox": [
        56.82,
        253.49,
        499.56,
        19.55
      ],
      "category_id": 1,
      "category_name": ""
    },
    {
      "bbox": [
        56.82,
        169.01,
        378.44,
        9.53
      ],
      "category_id": 1,
      "category_name": ""
    },
    {
      "bbox": [
        56.82,
        134.75,
        336.54,
        14.33
      ],
      "category_id": 1,
      "category_name": ""
    },
    {
      "bbox": [
        56.82,
        97.26,
        436.75,
        36.78
      ],
      "category_id": 2,
      "category_name": ""
    },
    {
      "bbox": [
        56.82,
        292.44,
        43.14,
        12.64
      ],
      "category_id": 2,
      "category_name": ""
    },
    {
      "bbox": [
        56.82,
        561.54,
        64.28,
        12.92
      ],
      "category_id": 2,
      "category_name": ""
    }
  ],
  "corruption": {
    "type": "none",
    "severity": 0
  }
}