{
  "file_name": "doc_03153.png",
  "annotations": [
    {
      "bbox": [
        55.14,
        601.71,
        240.99,
        58.11
      ],
      "category_id": 1,
      "category_name": ""
    },
    {
      "bbox": [
        313.08,
        601.72,
        240.98,
        58.11
      ],
      "category_id": 1,
      "category_name": ""
    },
    {
      "bbox": [
        55.14,
        672.22,
        240.99,
        58.11
      ],
      "category_id": 1,
      "category_name": ""
    },
    {
      "bbox": [
        313.08,
        683.91,
        240.98,
        46.41
      ],
      "category_id": 1,
      "category_name": ""
    },
    {
      "bbox": [
        55.14,
        84.77,
        477.96,
        18.89
      ],
      "category_id": 1,
      "category_name": ""
    },
    {
      "bbox": [
        59.1,
        549.87,
        491.56,
        37.32
      ],
      "category_id": 1,
      "category_name": ""
    },
    {
      "bbox": [
        55.14,
        110.28,
        499.98,
        433.92
      ],
      "category_id": 4,
      "category_name": ""
    },
    {
      "bbox": [
        313.08,
        671.53,
        55.56,
        12.66
      ],
      "category_id": 2,
      "category_name": ""
    }
  ],
  "corruption": {
    "type": "none",
    "severity": 0
  }
}