{
  "file_name": "doc_01240.png",
  "annotations": [
    {
      "bbox": [
        315.3,
        564.38,
        240.42,
        22.73
      ],
      "category_id": 1,
      "category_name": ""
    },
    {
      "bbox": [
        56.82,
        564.39,
        240.48,
        163.73
      ],
      "category_id": 1,
      "category_name": ""
    },
    {
      "bbox": [
        315.3,
        599.6,
        240.54,
        93.29
      ],
      "category_id": 1,
      "category_name": ""
    },
    {
      "bbox": [
        315.3,
        705.38,
        240.42,
        22.73
      ],
      "category_id": 1,
      "category_name": ""
    },
    {
      "bbox": [
        56.82,
        279.73,
        499.08,
        47.67
      ],
      "category_id": 1,
      "category_name": ""
    },
    {
      "bbox": [
        56.82,
        360.15,
        436.6,
        9.39
      ],
      "category_id": 1,
      "category_name": ""
    },
    {
      "bbox": [
        60.84,
        539.95,
        374.69,
        9.57
      ],
      "category_id": 1,
      "category_name": ""
    },
    {
      "bbox": [
        56.82,
        372.36,
        498.9,
        166.02
      ],
      "category_id": 4,
      "category_name": ""
    },
    {
      "bbox": [
        56.82,
        95.1,
        499.12,
        178.17
      ],
      "category_id": 5,
      "category_name": ""
    },
    {
      "bbox": [
        56.82,
        82.83,
        31.28,
        9.39
      ],
      "category_id": 2,
      "category_name": ""
    },
    {
      "bbox": [
        56.82,
        341.37,
        27.76,
        9.39
      ],
      "category_id": 2,
      "category_name": ""
    }
  ],
  "corruption": {
    "type": "none",
    "severity": 0
  }
}