{
  "file_name": "doc_02706.png",
  "annotations": [
    {
      "bbox": [
        55.14,
        84.69,
        240.98,
        152.13
      ],
      "category_id": 1,
      "category_name": ""
    },
    {
      "bbox": [
        55.14,
        249.16,
        240.98,
        222.63
      ],
      "category_id": 1,
      "category_name": ""
    },
    {
      "bbox": [
        55.14,
        484.18,
        240.97,
        34.65
      ],
      "category_id": 1,
      "category_name": ""
    },
    {
      "bbox": [
        55.14,
        554.67,
        240.98,
        93.39
      ],
      "category_id": 1,
      "category_name": ""
    },
    {
      "bbox": [
        55.14,
        659.81,
        195.72,
        13.48
      ],
      "category_id": 1,
      "category_name": ""
    },
    {
      "bbox": [
        55.14,
        683.29,
        209.99,
        13.52
      ],
      "category_id": 1,
      "category_name": ""
    },
    {
      "bbox": [
        55.14,
        706.82,
        240.91,
        23.51
      ],
      "category_id": 1,
      "category_name": ""
    },
    {
      "bbox": [
        313.08,
        96.39,
        240.98,
        293.19
      ],
      "category_id": 1,
      "category_name": ""
    },
    {
      "bbox": [
        313.08,
        401.92,
        240.97,
        81.63
      ],
      "category_id": 1,
      "category_name": ""
    },
    {
      "bbox": [
        313.08,
        507.69,
        240.99,
        116.85
      ],
      "category_id": 1,
      "category_name": ""
    },
    {
      "bbox": [
        313.08,
        648.69,
        241.0,
        46.35
      ],
      "category_id": 1,
      "category_name": ""
    },
    {
      "bbox": [
        313.08,
        707.44,
        240.98,
        22.89
      ],
      "category_id": 1,
      "category_name": ""
    },
    {
      "bbox": [
        55.14,
        530.53,
        114.75,
        12.66
      ],
      "category_id": 2,
      "category_name": ""
    },
    {
      "bbox": [
        55.14,
        542.78,
        67.57,
        11.04
      ],
      "category_id": 2,
      "category_name": ""
    },
    {
      "bbox": [
        313.08,
        84.5,
        88.42,
        11.04
      ],
      "category_id": 2,
      "category_name": ""
    },
    {
      "bbox": [
        313.08,
        495.74,
        141.36,
        11.04
      ],
      "category_id": 2,
      "category_name": ""
    },
    {
      "bbox": [
        313.08,
        636.74,
        230.6,
        11.04
      ],
      "category_id": 2,
      "category_name": ""
    }
  ],
  "corruption": {
    "type": "blur",
    "severity": 2
  }
}