{
  "file_name": "doc_01717.png",
  "annotations": [
    {
      "bbox": [
        107.87,
        238.23,
        394.53,
        37.89
      ],
      "category_id": 1,
      "category_name": ""
    },
    {
      "bbox": [
        107.87,
        319.03,
        394.53,
        102.65
      ],
      "category_id": 1,
      "category_name": ""
    },
    {
      "bbox": [
        107.87,
        464.58,
        394.52,
        50.84
      ],
      "category_id": 1,
      "category_name": ""
    },
    {
      "bbox": [
        107.87,
        516.39,
        394.52,
        24.94
      ],
      "category_id": 1,
      "category_name": ""
    },
    {
      "bbox": [
        107.87,
        542.29,
        394.52,
        37.89
      ],
      "category_id": 1,
      "category_name": ""
    },
    {
      "bbox": [
        194.51,
        117.9,
        215.76,
        10.96
      ],
      "category_id": 1,
      "category_name": ""
    },
    {
      "bbox": [
        191.03,
        600.7,
        199.67,
        10.97
      ],
      "category_id": 1,
      "category_name": ""
    },
    {
      "bbox": [
        198.12,
        199.15,
        216.11,
        18.68
      ],
      "category_id": 1,
      "category_name": ""
    },
    {
      "bbox": [
        194.64,
        692.92,
        224.27,
        18.68
      ],
      "category_id": 1,
      "category_name": ""
    },
    {
      "bbox": [
        194.51,
        132.83,
        221.23,
        63.67
      ],
      "category_id": 4,
      "category_name": ""
    },
    {
      "bbox": [
        191.03,
        615.65,
        228.19,
        74.62
      ],
      "category_id": 4,
      "category_name": ""
    },
    {
      "bbox": [
        107.87,
        298.88,
        128.14,
        12.21
      ],
      "category_id": 2,
      "category_name": ""
    },
    {
      "bbox": [
        107.87,
        444.43,
        98.75,
        12.21
      ],
      "category_id": 2,
      "category_name": ""
    }
  ],
  "corruption": {
    "type": "none",
    "severity": 0
  }
}