{
  "file_name": "doc_04430.png",
  "annotations": [
    {
      "bbox": [
        55.2,
        81.37,
        238.79,
        44.16
      ],
      "category_id": 1,
      "category_name": ""
    },
    {
      "bbox": [
        55.2,
        125.26,
        238.81,
        154.23
      ],
      "category_id": 1,
      "category_name": ""
    },
    {
      "bbox": [
        55.2,
        466.33,
        238.86,
        165.24
      ],
      "category_id": 1,
      "category_name": ""
    },
    {
      "bbox": [
        55.2,
        664.14,
        238.81,
        66.43
      ],
      "category_id": 1,
      "category_name": ""
    },
    {
      "bbox": [
        318.0,
        81.37,
        238.79,
        33.12
      ],
      "category_id": 1,
      "category_name": ""
    },
    {
      "bbox": [
        318.0,
        323.41,
        238.83,
        165.12
      ],
      "category_id": 1,
      "category_name": ""
    },
    {
      "bbox": [
        318.0,
        488.41,
        238.87,
        220.08
      ],
      "category_id": 1,
      "category_name": ""
    },
    {
      "bbox": [
        318.0,
        708.37,
        238.8,
        22.2
      ],
      "category_id": 1,
      "category_name": ""
    },
    {
      "bbox": [
        55.2,
        290.41,
        238.81,
        165.12
      ],
      "category_id": 3,
      "category_name": ""
    },
    {
      "bbox": [
        318.0,
        125.41,
        238.82,
        187.08
      ],
      "category_id": 3,
      "category_name": ""
    },
    {
      "bbox": [
        55.2,
        641.53,
        168.84,
        12.11
      ],
      "category_id": 2,
      "category_name": ""
    }
  ],
  "corruption": {
    "type": "rotate",
    "severity": 1
  }
}