{
  "file_name": "doc_02691.png",
  "annotations": [
    {
      "bbox": [
        56.82,
        391.44,
        240.5,
        137.07
      ],
      "category_id": 1,
      "category_name": ""
    },
    {
      "bbox": [
        56.82,
        538.5,
        240.48,
        74.01
      ],
      "category_id": 1,
      "category_name": ""
    },
    {
      "bbox": [
        315.3,
        391.49,
        240.54,
        126.52
      ],
      "category_id": 1,
      "category_name": ""
    },
    {
      "bbox": [
        315.3,
        538.47,
        240.51,
        74.05
      ],
      "category_id": 1,
      "category_name": ""
    },
    {
      "bbox": [
        315.3,
        651.27,
        240.51,
        34.55
      ],
      "category_id": 1,
      "category_name": ""
    },
    {
      "bbox": [
        56.82,
        663.03,
        240.4,
        22.79
      ],
      "category_id": 1,
      "category_name": ""
    },
    {
      "bbox": [
        56.82,
        703.07,
        499.14,
        38.03
      ],
      "category_id": 1,
      "category_name": ""
    },
    {
      "bbox": [
        56.82,
        331.97,
        499.56,
        19.55
      ],
      "category_id": 1,
      "category_name": ""
    },
    {
      "bbox": [
        56.82,
        218.96,
        390.49,
        38.06
      ],
      "category_id": 1,
      "category_name": ""
    },
    {
      "bbox": [
        56.82,
        152.66,
        463.33,
        46.39
      ],
      "category_id": 1,
      "category_name": ""
    },
    {
      "bbox": [
        56.82,
        97.26,
        493.77,
        54.78
      ],
      "category_id": 2,
      "category_name": ""
    },
    {
      "bbox": [
        56.82,
        370.98,
        43.14,
        12.64
      ],
      "category_id": 2,
      "category_name": ""
    },
    {
      "bbox": [
        56.82,
        650.58,
        64.28,
        12.92
      ],
      "category_id": 2,
      "category_name": ""
    }
  ],
  "corruption": {
    "type": "none",
    "severity": 0
  }
}