{
  "file_name": "doc_03320.png",
  "annotations": [
    {
      "bbox": [
        111.84,
        343.81,
        385.62,
        58.74
      ],
      "category_id": 1,
      "category_name": ""
    },
    {
      "bbox": [
        111.84,
        408.01,
        385.62,
        70.03
      ],
      "category_id": 1,
      "category_name": ""
    },
    {
      "bbox": [
        111.84,
        483.49,
        385.6,
        117.06
      ],
      "category_id": 1,
      "category_name": ""
    },
    {
      "bbox": [
        313.08,
        638.92,
        240.98,
        58.11
      ],
      "category_id": 1,
      "category_name": ""
    },
    {
      "bbox": [
        55.14,
        650.67,
        241.0,
        81.63
      ],
      "category_id": 1,
      "category_name": ""
    },
    {
      "bbox": [
        313.08,
        709.42,
        240.95,
        22.89
      ],
      "category_id": 1,
      "category_name": ""
    },
    {
      "bbox": [
        55.14,
        276.55,
        492.36,
        18.74
      ],
      "category_id": 1,
      "category_name": ""
    },
    {
      "bbox": [
        55.14,
        156.12,
        391.02,
        9.14
      ],
      "category_id": 1,
      "category_name": ""
    },
    {
      "bbox": [
        55.14,
        119.37,
        241.9,
        17.18
      ],
      "category_id": 1,
      "category_name": ""
    },
    {
      "bbox": [
        55.14,
        100.53,
        489.69,
        18.82
      ],
      "category_id": 2,
      "category_name": ""
    },
    {
      "bbox": [
        111.84,
        328.93,
        43.92,
        12.66
      ],
      "category_id": 2,
      "category_name": ""
    },
    {
      "bbox": [
        55.14,
        638.23,
        60.3,
        12.66
      ],
      "category_id": 2,
      "category_name": ""
    }
  ],
  "corruption": {
    "type": "none",
    "severity": 0
  }
}